pyverm/__init__.py
pyverm/__meta__.py
pyverm/_classes.py
pyverm/_functions.py
pyverm/_transformation.py
pyverm/_utils.py
pyverm/api.py
pyverm/settings.py
pyverm/geocom/__init__.py
pyverm/geocom/geocom.py
pyverm/tests/__init__.py
pyverm/tests/test__classes.py
pyverm/tests/test__functions.py
pyverm/tests/test__transformation.py
pyverm/tests/test__utils.py
pyverm/tests/test_examples.py
pyverm/tests/test_pyverm.py
pyverm/tests/test_settings.py
pyverm-0.3.0.dist-info/LICENSE
pyverm-0.3.0.dist-info/METADATA
pyverm-0.3.0.dist-info/WHEEL
pyverm-0.3.0.dist-info/top_level.txt
pyverm-0.3.0.dist-info/RECORD
